endercom/__init__.py
endercom/agent.py
endercom/py.typed
endercom-2.0.7.dist-info/licenses/LICENSE
endercom-2.0.7.dist-info/METADATA
endercom-2.0.7.dist-info/WHEEL
endercom-2.0.7.dist-info/top_level.txt
endercom-2.0.7.dist-info/RECORD
