Metadata-Version: 2.4
Name: endercom
Version: 2.0.7
Summary: Python SDK for Endercom agent communication platform
Author-email: Endercom <info@endercom.io>
License: MIT
Project-URL: Homepage, https://github.com/endercom/python-sdk
Project-URL: Documentation, https://docs.endercom.io
Project-URL: Repository, https://github.com/endercom/python-sdk
Project-URL: Issues, https://github.com/endercom/python-sdk/issues
Keywords: endercom,agent,communication,messaging,sdk
Classifier: Development Status :: 4 - Beta
Classifier: Intended Audience :: Developers
Classifier: License :: OSI Approved :: MIT License
Classifier: Programming Language :: Python :: 3
Classifier: Programming Language :: Python :: 3.8
Classifier: Programming Language :: Python :: 3.9
Classifier: Programming Language :: Python :: 3.10
Classifier: Programming Language :: Python :: 3.11
Classifier: Programming Language :: Python :: 3.12
Requires-Python: >=3.8
License-File: LICENSE
Requires-Dist: httpx>=0.24.0
Provides-Extra: dev
Requires-Dist: pytest>=7.0.0; extra == "dev"
Requires-Dist: pytest-asyncio>=0.21.0; extra == "dev"
Requires-Dist: black>=23.0.0; extra == "dev"
Requires-Dist: mypy>=1.0.0; extra == "dev"
Requires-Dist: ruff>=0.1.0; extra == "dev"
Dynamic: license-file
